{"name":"libbmp24","tagline":"SIMPLE and TINY bitmap image library.","body":"#DESCRIPTION\r\nlibbmp24 is SIMPLE and TINY bitmap image C++ library.\r\nThis library is composed of ONE header file, so it is very portable program. Windows, Mac, UNIX, and more platform can use libbmp24.\r\n\r\n# SUPPORT FORMAT\r\n24bit bitmap (true color) only.\r\n\r\n\r\n# USAGE\r\nlibbmp24 can easily be imported into your C++ project.\r\nJust include one header file only.\r\n\r\n    #include \"libbmp24.hpp\"\r\n\r\n### Sample 01.\r\nLoad bmp and rename save.\r\n\r\n    int main() {\r\n        libbmp24::Bitmap bmp;\r\n        \r\n        // Load bmp.\r\n        std::ifstream is(\"src.bmp\", std::ios::in);\r\n        bmp.deserialize(is);\r\n        // Rename and Save.\r\n        std::ofstream os(\"dest.bmp\", std::ios::out);\r\n        bmp.serialize(os);\r\n        return 0;\r\n    }\r\n\r\n\r\n\r\n### Sample02.\r\nDump bitmap file information to console window.\r\n\r\n    int main() {\r\n        std::ifstream is(\"src.bmp\", std::ios::in);\r\n        libbmp24::Bitmap bmp;\r\n        bmp.dump();\r\n        return 0;\r\n    }\r\n    \r\n### Sample03.\r\nCreate new bitmap file.\r\n\r\n    int main() {\r\n        libbmp24::Bitmap bmp;\r\n        const int width = 64;\r\n        const int height = 100;\r\n        bmp.createBitmap(width, height); // create new bitmap.\r\n        bmp.fill(255, 0, 30); // r, g, b\r\n        // save.\r\n        std::ifstream os(\"dest.bmp\", std::ios::in);\r\n        bmp.deserialize(os);\r\n        return 0;\r\n    }\r\n    \r\n\r\n\r\n# LICENSE\r\n\r\nlibbmp24 is released under the zlib license.\r\n\r\nPlease read [LICENSE](https://github.com/doscoy/libbmp24/blob/master/LICENSE) file.\r\n    \r\n","google":"","note":"Don't delete this file! It's used internally to help with page regeneration."}